flipkart/__init__.py
flipkart/scraper.py
abhi_flipkart-1.0.2.dist-info/LICENSE
abhi_flipkart-1.0.2.dist-info/METADATA
abhi_flipkart-1.0.2.dist-info/WHEEL
abhi_flipkart-1.0.2.dist-info/top_level.txt
abhi_flipkart-1.0.2.dist-info/RECORD
